bbp4adg/__init__.py
bbp4adg/estimators/__init__.py
bbp4adg/estimators/adg.py
bbp4adg/estimators/base.py
bbp4adg/estimators/bbp.py
bbp4adg/estimators/model.py
bbp4adg/estimators/semantics.py
bbp4adg/utils/__init__.py
bbp4adg/utils/data.py
bbp4adg/utils/logger.py
bbp4adg-0.1.0.dist-info/LICENSE
bbp4adg-0.1.0.dist-info/METADATA
bbp4adg-0.1.0.dist-info/WHEEL
bbp4adg-0.1.0.dist-info/top_level.txt
bbp4adg-0.1.0.dist-info/RECORD
