Metadata-Version: 2.1
Name: bbp4adg
Version: 0.1.0
Summary: BoostedBuidlingProcessForADG
Home-page: https://github.com/S2thend/BoostedBuidlingProcessForADG
Author: Borui Cai
Author-email: borui_cai@qq.com
License: UNKNOWN
Platform: UNKNOWN
Classifier: Programming Language :: Python :: 3
Classifier: License :: OSI Approved :: MIT License
Classifier: Operating System :: OS Independent
Requires-Python: >=3.6
Requires-Dist: numpy (==1.24.4)
Requires-Dist: pandas (==2.0.3)
